[{
    "title": "Rumah Taman International, Citraland",
    "propertyType": "house",
    "listingType": "sale",
    "address": "",
    "price": 10000000000,
    "lotSize": 570,
    "buildingSize": 200,
    "carCount": 0,
    "bedroomCount": 4,
    "additionalBedroomCount": 1,
    "bathroomCount": 3,
    "additionalBathroomCount": 0,
    "floorCount": 1,
    "electricPower" : 0,
    "facing": "southeast",
    "ownership": "shm",
    "city": "",
    "pictureUrls": [],
    "contact": {
        "name": "Hana",
        "phoneNumber": "082142780083",
        "company": "XM Royal Residence Point"
    }
}]
